asyncscope/__init__.py
tests/__init__.py
tests/test_basic.py
asyncscope-0.11.2.dist-info/METADATA
asyncscope-0.11.2.dist-info/WHEEL
asyncscope-0.11.2.dist-info/top_level.txt
asyncscope-0.11.2.dist-info/RECORD
