Metadata-Version: 2.1
Name: asyncscope
Version: 0.11.2
Summary: Task scopes for AnyIO
Home-page: http://github.com/M-o-a-T/asyncscope
Author: Matthias Urlichs
Author-email: matthias@urlichs.de
License: GPLv3 or later
Keywords: async
Classifier: License :: OSI Approved :: GNU General Public License v3 or later (GPLv3+)
Classifier: Operating System :: POSIX :: Linux
Classifier: Programming Language :: Python :: 3 :: Only
Classifier: Programming Language :: Python :: 3.7
Classifier: Programming Language :: Python :: 3.8
Classifier: Programming Language :: Python :: Implementation :: CPython
Classifier: Programming Language :: Python :: Implementation :: PyPy
Classifier: Framework :: Trio
Classifier: Framework :: AsyncIO
Requires-Python: >=3.6
Requires-Dist: anyio (>=4)
Requires-Dist: trio (>=0.22)
